{
  "required": true,
  "minVersion": "0.8",
  "package": "top.theillusivec4.colytra.loader.mixin",
  "compatibilityLevel": "JAVA_8",
  "mixins": [
    "AnvilScreenHandlerAccessor",
    "AnvilScreenHandlerMixin",
    "ExperienceOrbEntityAccessor",
    "ExperienceOrbEntityMixin",
    "ForgingScreenHandlerAccessor",
    "LivingEntityAccessor",
    "PlayerEntityMixin",
    "PlayerManagerMixin",
    "ReloadCommandMixin"
  ],
  "client": ["ItemStackMixin"],
  "server": [],
  "injectors": {
    "defaultRequire": 1
  }
}